ssh_manager/__init__.py
ssh_manager/database.py
ssh_manager/models.py
ssh_manager/ssh_manager.py
loginssh-0.1.dist-info/METADATA
loginssh-0.1.dist-info/WHEEL
loginssh-0.1.dist-info/entry_points.txt
loginssh-0.1.dist-info/top_level.txt
loginssh-0.1.dist-info/RECORD
