Metadata-Version: 2.1
Name: loginssh
Version: 0.1
Summary: A tool to manage SSH connections and their passwords
Home-page: http://packages.python.org/an_example_pypi_project
Author: Kaustubh Maske Patil
Author-email: ktvm42@gmail.com
License: MIT
Keywords: ssh ssh-manager
Platform: UNKNOWN
Classifier: Topic :: Utilities
Classifier: License :: OSI Approved :: MIT License
Requires-Python: >3.8.0
